euterpe/__init__.py
euterpe/api.py
euterpe/cli.py
euterpe/commands/__init__.py
euterpe/commands/accounts.py
euterpe/commands/server.py
euterpe/core/__init__.py
euterpe/core/crud.py
euterpe/core/database.py
euterpe/core/models.py
euterpe/core/schemas.py
euterpe-0.2.2.dist-info/METADATA
euterpe-0.2.2.dist-info/WHEEL
euterpe-0.2.2.dist-info/RECORD
