Metadata-Version: 2.1
Name: euterpe
Version: 0.2.2
Summary: 
Author: Brice Santus
Author-email: brice.santus@proton.me
Requires-Python: >=3.10,<4.0
Classifier: Programming Language :: Python :: 3
Classifier: Programming Language :: Python :: 3.10
Classifier: Programming Language :: Python :: 3.11
Requires-Dist: fastapi (>=0.103.1,<0.104.0)
Requires-Dist: mfrc522 (>=0.0.7,<0.0.8)
Requires-Dist: spidev (>=3.6,<4.0)
Requires-Dist: spotipy (>=2.23.0,<3.0.0)
Requires-Dist: sqlalchemy (>=2.0.20,<3.0.0)
Requires-Dist: typer[all] (>=0.9.0,<0.10.0)
Requires-Dist: uvicorn (>=0.23.2,<0.24.0)
